auto_doc_loader-0.1.0.dist-info/licenses/LICENSE.txt
auto_loader/__init__.py
auto_loader/auto_doc_loader.py
test_loader/test_loader.py
auto_doc_loader-0.1.0.dist-info/METADATA
auto_doc_loader-0.1.0.dist-info/WHEEL
auto_doc_loader-0.1.0.dist-info/top_level.txt
auto_doc_loader-0.1.0.dist-info/RECORD
