Metadata-Version: 2.4
Name: auto_doc_loader
Version: 0.1.0
Summary: AutoLoader for structured and unstructured documents using LangChain
Home-page: https://github.com/Mahemaran/auto_loader
Author: Maran M
Author-email: Maran M <mahemaran99@gmail.com>
License: Apache 2.0
Project-URL: Homepage, https://github.com/Mahemaran/auto_loader
Project-URL: Repository, https://github.com/Mahemaran/auto_loader
Classifier: Programming Language :: Python :: 3
Classifier: License :: OSI Approved :: Apache Software License
Classifier: Operating System :: OS Independent
Requires-Python: >=3.8
License-File: LICENSE.txt
Requires-Dist: langchain
Requires-Dist: langchain-unstructured
Dynamic: author
Dynamic: home-page
Dynamic: license-file
Dynamic: requires-python
